{
	"name": "DelimitedText1",
	"properties": {
		"linkedServiceName": {
			"referenceName": "AzureBlobStorage2",
			"type": "LinkedServiceReference"
		},
		"annotations": [],
		"type": "DelimitedText",
		"typeProperties": {
			"location": {
				"type": "AzureBlobStorageLocation",
				"fileName": "bank-additional-full.csv",
				"container": "source"
			},
			"columnDelimiter": ",",
			"escapeChar": "\\",
			"firstRowAsHeader": true,
			"quoteChar": "\""
		},
		"schema": [
			{
				"name": "\"age\";\"job\";\"marital\";\"education\";\"default\";\"housing\";\"loan\";\"contact\";\"month\";\"day_of_week\";\"duration\";\"campaign\";\"pdays\";\"previous\";\"poutcome\";\"emp.var.rate\";\"cons.price.idx\";\"cons.conf.idx\";\"euribor3m\";\"nr.employed\";\"y\"",
				"type": "String"
			}
		]
	},
	"type": "Microsoft.DataFactory/factories/datasets"
}